image_deduplication/__init__.py
image_deduplication/cli.py
image_deduplication/main.py
image_deduplication-0.1.3.dist-info/LICENSE
image_deduplication-0.1.3.dist-info/METADATA
image_deduplication-0.1.3.dist-info/WHEEL
image_deduplication-0.1.3.dist-info/entry_points.txt
image_deduplication-0.1.3.dist-info/top_level.txt
image_deduplication-0.1.3.dist-info/RECORD
